{"config": {"view": {"continuousWidth": 300, "continuousHeight": 300}, "legend": {"orient": "bottom"}}, "data": {"name": "data-1b1626188e7969cf07b13e8f029e3c84"}, "mark": {"type": "bar"}, "encoding": {"x": {"axis": {"labelAngle": -4}, "field": "month_year", "title": "Months", "type": "temporal"}, "y": {"field": "books_scanned", "title": "Books Scanned", "type": "quantitative"}}, "height": 400, "params": [{"name": "param_19", "select": {"type": "interval", "encodings": ["x", "y"]}, "bind": "scales"}], "width": "container", "$schema": "https://vega.github.io/schema/vega-lite/v5.8.0.json", "datasets": {"data-1b1626188e7969cf07b13e8f029e3c84": [{"name": "Clemson University", "month_year": "2012-02", "books_scanned": 31}, {"name": "Clemson University", "month_year": "2012-03", "books_scanned": 334}, {"name": "Clemson University", "month_year": "2012-04", "books_scanned": 325}, {"name": "Clemson University", "month_year": "2012-05", "books_scanned": 456}, {"name": "Clemson University", "month_year": "2012-06", "books_scanned": 458}, {"name": "Clemson University", "month_year": "2012-07", "books_scanned": 555}, {"name": "Clemson University", "month_year": "2012-08", "books_scanned": 415}, {"name": "Clemson University", "month_year": "2012-09", "books_scanned": 470}, {"name": "Clemson University", "month_year": "2012-10", "books_scanned": 498}, {"name": "Clemson University", "month_year": "2012-11", "books_scanned": 347}, {"name": "Clemson University", "month_year": "2012-12", "books_scanned": 118}, {"name": "Clemson University", "month_year": "2013-01", "books_scanned": 381}, {"name": "Clemson University", "month_year": "2013-02", "books_scanned": 435}, {"name": "Clemson University", "month_year": "2013-03", "books_scanned": 193}, {"name": "Clemson University", "month_year": "2013-04", "books_scanned": 381}, {"name": "Clemson University", "month_year": "2013-05", "books_scanned": 243}, {"name": "Clemson University", "month_year": "2013-06", "books_scanned": 451}, {"name": "Clemson University", "month_year": "2013-07", "books_scanned": 188}, {"name": "Clemson University", "month_year": "2013-08", "books_scanned": 252}, {"name": "Clemson University", "month_year": "2013-09", "books_scanned": 193}, {"name": "Clemson University", "month_year": "2013-10", "books_scanned": 321}, {"name": "Clemson University", "month_year": "2013-11", "books_scanned": 147}, {"name": "Clemson University", "month_year": "2013-12", "books_scanned": 198}, {"name": "Clemson University", "month_year": "2014-01", "books_scanned": 237}, {"name": "Clemson University", "month_year": "2014-02", "books_scanned": 487}, {"name": "Clemson University", "month_year": "2014-03", "books_scanned": 467}, {"name": "Clemson University", "month_year": "2014-04", "books_scanned": 402}, {"name": "Clemson University", "month_year": "2014-05", "books_scanned": 213}, {"name": "Clemson University", "month_year": "2014-06", "books_scanned": 411}, {"name": "Clemson University", "month_year": "2014-07", "books_scanned": 426}, {"name": "Clemson University", "month_year": "2014-08", "books_scanned": 240}, {"name": "Clemson University", "month_year": "2014-09", "books_scanned": 1}]}}